rusty_graph/__init__.py
rusty_graph/rusty_graph.cpython-313-x86_64-linux-gnu.so
rusty_graph-0.3.30.dist-info/METADATA
rusty_graph-0.3.30.dist-info/WHEEL
rusty_graph-0.3.30.dist-info/licenses/LICENSE
rusty_graph-0.3.30.dist-info/RECORD
