Metadata-Version: 2.4
Name: rusty_graph
Version: 0.3.30
Classifier: Development Status :: 4 - Beta
Classifier: Intended Audience :: Developers
Classifier: Intended Audience :: Science/Research
Classifier: License :: OSI Approved :: MIT License
Classifier: Operating System :: OS Independent
Classifier: Programming Language :: Python :: 3
Classifier: Programming Language :: Python :: 3.10
Classifier: Programming Language :: Python :: 3.11
Classifier: Programming Language :: Python :: 3.12
Classifier: Programming Language :: Python :: 3.13
Classifier: Programming Language :: Rust
Classifier: Programming Language :: Python :: Implementation :: CPython
Classifier: Programming Language :: Python :: Implementation :: PyPy
Classifier: Topic :: Database
Classifier: Topic :: Scientific/Engineering
Classifier: Topic :: Software Development :: Libraries :: Python Modules
License-File: LICENSE
Summary: A high-performance graph database library with Python bindings written in Rust
Keywords: graph,database,knowledge-graph,rust,high-performance,data-science
Author-email: Kristian dF Kollsgård <kkollsg@gmail.com>
License: MIT
Requires-Python: >=3.10
Project-URL: Documentation, https://github.com/kkollsga/rusty-graph#readme
Project-URL: Homepage, https://github.com/kkollsga/rusty-graph
Project-URL: Repository, https://github.com/kkollsga/rusty-graph
